README.rst
setup.py
finsky/__init__.py
finsky/cli.py
finsky/client.py
finsky.egg-info/PKG-INFO
finsky.egg-info/SOURCES.txt
finsky.egg-info/dependency_links.txt
finsky.egg-info/entry_points.txt
finsky.egg-info/requires.txt
finsky.egg-info/top_level.txt
finsky/protos/__init__.py
finsky/protos/ack_notification_pb2.py
finsky/protos/acquisition_pb2.py
finsky/protos/address_form_outer_class_pb2.py
finsky/protos/android_app_delivery_pb2.py
finsky/protos/api_pb2.py
finsky/protos/app_doc_details_pb2.py
finsky/protos/billing_address_pb2.py
finsky/protos/billing_profile_protos_pb2.py
finsky/protos/book_doc_details_pb2.py
finsky/protos/browse_pb2.py
finsky/protos/buy_instruments_pb2.py
finsky/protos/buy_pb2.py
finsky/protos/carrier_billing_pb2.py
finsky/protos/challenge_action_pb2.py
finsky/protos/challenge_proto_pb2.py
finsky/protos/check_promo_offer_pb2.py
finsky/protos/client_analytics_pb2.py
finsky/protos/common_device_pb2.py
finsky/protos/common_pb2.py
finsky/protos/consume_purchase_response_pb2.py
finsky/protos/containers_pb2.py
finsky/protos/content_filters_pb2.py
finsky/protos/content_flagging_pb2.py
finsky/protos/context_outer_class_pb2.py
finsky/protos/create_instrument_pb2.py
finsky/protos/credit_card_pb2.py
finsky/protos/csd_client_pb2.py
finsky/protos/customer_form_outer_class_pb2.py
finsky/protos/data_tokens_pb2.py
finsky/protos/dcb_pb2.py
finsky/protos/debug_info_proto_pb2.py
finsky/protos/debug_settings_pb2.py
finsky/protos/delivery_pb2.py
finsky/protos/details_pb2.py
finsky/protos/device_configuration_proto_pb2.py
finsky/protos/device_fingerprinting_pb2.py
finsky/protos/doc_annotations_pb2.py
finsky/protos/doc_details_pb2.py
finsky/protos/doc_list_pb2.py
finsky/protos/document_pb2.py
finsky/protos/document_v1_pb2.py
finsky/protos/document_v2_pb2.py
finsky/protos/early_update_pb2.py
finsky/protos/encrypted_subscriber_info_pb2.py
finsky/protos/filter_rules_pb2.py
finsky/protos/form_field_reference_outer_class_pb2.py
finsky/protos/form_header_outer_class_pb2.py
finsky/protos/group_license_pb2.py
finsky/protos/image_with_caption_outer_class_pb2.py
finsky/protos/info_message_outer_class_pb2.py
finsky/protos/instrument_form_outer_class_pb2.py
