Metadata-Version: 1.0
Name: finsky
Version: 0.3.3
Summary: Google Play API
Home-page: https://github.com/mmcloughlin/finsky
Author: Michael McLoughlin
Author-email: mmcloughlin@gmail.com
License: MIT
Platform: UNKNOWN
